{
	"display": {
		"icon": {
			"item": "iguanatweaksexpanded:solarium_ball"
		},
		"title": {
			"translate": "advancements.sr_story.solarium.title"
		},
		"description": {
			"translate": "advancements.sr_story.solarium.description"
		},
		"frame": "task",
		"show_toast": true,
		"announce_to_chat": true,
		"hidden": false
	},
	"parent": "iguanatweaksexpanded:story/iron_pickaxe",
	"criteria": {
		"solarium": {
			"trigger": "minecraft:inventory_changed",
			"conditions": {
				"items": [
					{
						"items": [
							"iguanatweaksexpanded:solarium_pickaxe",
							"iguanatweaksexpanded:solarium_axe",
							"iguanatweaksexpanded:solarium_shovel",
							"iguanatweaksexpanded:solarium_hoe",
							"iguanatweaksexpanded:solarium_sword",
							"iguanatweaksexpanded:solarium_helmet",
							"iguanatweaksexpanded:solarium_chestplate",
							"iguanatweaksexpanded:solarium_leggings",
							"iguanatweaksexpanded:solarium_boots"
						]
					}
				]
			}
		}
	},
	"requirements": [
		[
			"solarium"
		]
	]
}